{
  "coverage": "100%",
  "expectCount": 57,
  "actualCount": 57,
  "files": {
    "ugraphics/dashrouter.js": {
      "expectCount": 1,
      "actualCount": 1,
      "undocumentLines": []
    },
    "ugraphics/server.js": {
      "expectCount": 4,
      "actualCount": 4,
      "undocumentLines": []
    },
    "ugraphics/shared.js": {
      "expectCount": 2,
      "actualCount": 2,
      "undocumentLines": []
    },
    "ugraphics/socketHandler.js": {
      "expectCount": 5,
      "actualCount": 5,
      "undocumentLines": []
    },
    "ugraphics/src/js/cg/animate.js": {
      "expectCount": 6,
      "actualCount": 6,
      "undocumentLines": []
    },
    "ugraphics/src/js/cg/cg.js": {
      "expectCount": 3,
      "actualCount": 3,
      "undocumentLines": []
    },
    "ugraphics/src/js/cg/cgcontroller.js": {
      "expectCount": 12,
      "actualCount": 12,
      "undocumentLines": []
    },
    "ugraphics/src/js/dash/dash.js": {
      "expectCount": 8,
      "actualCount": 8,
      "undocumentLines": []
    },
    "ugraphics/src/js/dash/dashcontroller.js": {
      "expectCount": 14,
      "actualCount": 14,
      "undocumentLines": []
    },
    "ugraphics/stylesheet.js": {
      "expectCount": 2,
      "actualCount": 2,
      "undocumentLines": []
    }
  }
}